gmailapi/__init__.py
gmailapi/attribute.py
gmailapi/draft.py
gmailapi/gmail.py
gmailapi/label.py
gmailapi/message.py
gmailapi/proxy.py
gmailapi/query.py
gmailapi-0.3.1.dist-info/LICENSE
gmailapi-0.3.1.dist-info/METADATA
gmailapi-0.3.1.dist-info/WHEEL
gmailapi-0.3.1.dist-info/top_level.txt
gmailapi-0.3.1.dist-info/RECORD
