Metadata-Version: 2.1
Name: gmailapi
Version: 0.3.1
Summary: A library providing Python bindings for the Gmail api.
Home-page: https://github.com/matthewgdv/gmailapi
Author: Matt GdV
Author-email: matthewgdv@gmail.com
License: MIT
Platform: UNKNOWN
Classifier: Development Status :: 3 - Alpha
Classifier: Intended Audience :: Developers
Classifier: Programming Language :: Python :: 3.8
Requires-Dist: emails
Requires-Dist: google-api-python-client
Requires-Dist: google-auth
Requires-Dist: google-auth-oauthlib
Requires-Dist: mail-parser
Requires-Dist: maybe-else
Requires-Dist: pathmagic
Requires-Dist: pysubtypes
Requires-Dist: pymiscutils
Requires-Dist: pyiotools
